cocpyth/__about__.py
cocpyth/__init__.py
cocpyth/__main__.py
cocpyth/data/__init__.py
cocpyth/data/extract_lnames.py
cocpyth/data/female_names.tsv
cocpyth/data/lnames.txt
cocpyth/data/male_names.tsv
cocpyth/data/occupations.yaml
cocpyth/data/skills.yaml
cocpyth/dtypes/__init__.py
cocpyth/dtypes/character.py
cocpyth/dtypes/dice.py
cocpyth/dtypes/occupation.py
cocpyth/dtypes/skill.py
cocpyth/dtypes/stat.py
cocpyth/generator/character.py
cocpyth/generator/name.py
cocpyth/prompts/default_responses.py
cocpyth/prompts/validation.py
cocpyth/utils/__init__.py
cocpyth/utils/io.py
cocpyth/utils/sheet.py
cocpyth/utils/weird_math.py
cocpyth-0.1.1.dist-info/METADATA
cocpyth-0.1.1.dist-info/WHEEL
cocpyth-0.1.1.dist-info/entry_points.txt
cocpyth-0.1.1.dist-info/licenses/LICENSE.txt
cocpyth-0.1.1.dist-info/RECORD
