Metadata-Version: 2.1
Name: cocpyth
Version: 0.1.1
Summary: Command line interface to generate Call of Cthulhu characters
Project-URL: Documentation, https://github.com/TheOafidian/cocpyth#readme
Project-URL: Issues, https://github.com/TheOafidian/cocpyth/issues
Project-URL: Source, https://github.com/TheOafidian/cocpyth
Author-email: TheOafidian <tim.van.rillaer@hotmail.com>
License-Expression: MIT
License-File: LICENSE.txt
Keywords: Call,Character,Cthulhu,Generator,cli,of
Classifier: Development Status :: 4 - Beta
Classifier: Programming Language :: Python
Classifier: Programming Language :: Python :: 3.7
Classifier: Programming Language :: Python :: 3.8
Classifier: Programming Language :: Python :: 3.9
Classifier: Programming Language :: Python :: 3.10
Classifier: Programming Language :: Python :: 3.11
Classifier: Programming Language :: Python :: Implementation :: CPython
Classifier: Programming Language :: Python :: Implementation :: PyPy
Requires-Python: >=3.7
Requires-Dist: annotated-types==0.6.0
Requires-Dist: cocpyth==0.1.1
Requires-Dist: numpy==1.24.4
Requires-Dist: pandas==2.0.3
Requires-Dist: prompt-toolkit==3.0.43
Requires-Dist: pyaml==23.9.7
Requires-Dist: pydantic-core==2.10.1
Requires-Dist: pydantic==2.4.2
Requires-Dist: pypdf==3.8.1
Requires-Dist: python-dateutil==2.8.2
Requires-Dist: pytz==2023.3.post1
Requires-Dist: pyyaml==6.0.1
Requires-Dist: six==1.16.0
Requires-Dist: tabulate==0.9.0
Requires-Dist: typing-extensions==4.8.0
Requires-Dist: tzdata==2023.4
Requires-Dist: wcwidth==0.2.12
